setup.py
unicode2utf8/__init__.py
unicode2utf8/unicode2utf8.py
unicode2utf8.egg-info/PKG-INFO
unicode2utf8.egg-info/SOURCES.txt
unicode2utf8.egg-info/dependency_links.txt
unicode2utf8.egg-info/top_level.txt