Metadata-Version: 1.1
Name: unicode2utf8
Version: 1.0.0
Summary: Changes encoding from unicode to utf-8
Home-page: https://github.com/miguelbeltre/unicode2utf8
Author: Miguel E. Beltre
Author-email: miguelbeltre@packlink.com
License: UNKNOWN
Platform: UNKNOWN
Classifier: Programming Language :: Python
Classifier: Programming Language :: Python :: 2
Classifier: Operating System :: OS Independent
Classifier: Intended Audience :: Developers
